topsis_kshitiz_102303748/__init__.py
topsis_kshitiz_102303748/topsis.py
topsis_kshitiz_102303748-0.1.2.dist-info/licenses/LICENSE
topsis_kshitiz_102303748-0.1.2.dist-info/METADATA
topsis_kshitiz_102303748-0.1.2.dist-info/WHEEL
topsis_kshitiz_102303748-0.1.2.dist-info/entry_points.txt
topsis_kshitiz_102303748-0.1.2.dist-info/top_level.txt
topsis_kshitiz_102303748-0.1.2.dist-info/RECORD
