Metadata-Version: 2.4
Name: Topsis-Kshitiz-102303748
Version: 0.1.2
Summary: TOPSIS CLI with automatic categorical handling
Author: Kshitiz
License: MIT
Keywords: topsis,decision-making,mcdm,multi-criteria,ranking
Classifier: Development Status :: 4 - Beta
Classifier: Intended Audience :: Science/Research
Classifier: License :: OSI Approved :: MIT License
Classifier: Programming Language :: Python :: 3
Classifier: Programming Language :: Python :: 3.8
Classifier: Programming Language :: Python :: 3.9
Classifier: Programming Language :: Python :: 3.10
Classifier: Programming Language :: Python :: 3.11
Classifier: Topic :: Scientific/Engineering
Requires-Python: >=3.8
License-File: LICENSE
Requires-Dist: pandas>=1.5
Requires-Dist: numpy>=1.23
Dynamic: license-file
